autoupgrade/__init__.py
autoupgrade/exceptions.py
autoupgrade/package.py
autoupgrade/utils.py
autoupgrade_ng-0.3.0.dist-info/DESCRIPTION.rst
autoupgrade_ng-0.3.0.dist-info/METADATA
autoupgrade_ng-0.3.0.dist-info/RECORD
autoupgrade_ng-0.3.0.dist-info/WHEEL
autoupgrade_ng-0.3.0.dist-info/metadata.json
autoupgrade_ng-0.3.0.dist-info/top_level.txt
autoupgrade_ng-0.3.0.dist-info/zip-safe
