Metadata-Version: 2.0
Name: autoupgrade-ng
Version: 0.3.0
Summary: Automatic upgrade of PyPI packages
Home-page: https://github.com/vuolter/autoupgrade
Author: Walter Purcaro
Author-email: vuolter@gmail.com
License: UNKNOWN
Download-URL: https://github.com/vuolter/autoupgrade/releases
Keywords: autoupgrade,pip-upgrade,pip
Platform: UNKNOWN
Classifier: Development Status :: 5 - Production/Stable
Classifier: Environment :: Other Environment
Classifier: License :: OSI Approved :: MIT License
Classifier: Intended Audience :: Developers
Classifier: Intended Audience :: System Administrators
Classifier: Operating System :: OS Independent
Classifier: Programming Language :: Python
Classifier: Programming Language :: Python :: 2
Classifier: Programming Language :: Python :: 3
Classifier: Topic :: System :: Software Distribution
Classifier: Topic :: Utilities
Obsoletes: autoupgrade
Requires-Dist: pip
